sgen/__init__.py
sgen/base.py
sgen/dto.py
sgen/fields.py
sgen/sgen.py
sgen/utils.py
sgen/validate.py
sgen-1.0.2.dist-info/METADATA
sgen-1.0.2.dist-info/WHEEL
sgen-1.0.2.dist-info/top_level.txt
sgen-1.0.2.dist-info/RECORD
