Metadata-Version: 2.1
Name: sgen
Version: 1.0.2
Summary: Generating test data structures
Home-page: https://github.com/Apels1nA/sgen/
Author: Ilya Verner
License: MIT
Project-URL: Repo, https://github.com/Apels1nA/sgen
Project-URL: Docs, https://sgen.readthedocs.io/en/latest/index.html
Project-URL: Changelog, https://sgen.readthedocs.io/en/latest/changelog.html
Project-URL: Issues, https://github.com/Apels1nA/sgen/issues
Keywords: generate,data,json,test,schema,structure
Requires-Python: >=3.8
Requires-Dist: packaging >=17.0
Provides-Extra: docs
Requires-Dist: sphinx ==7.2.6 ; extra == 'docs'
Requires-Dist: sphinx-issues ==3.0.1 ; extra == 'docs'
Requires-Dist: alabaster ==0.7.13 ; extra == 'docs'
Provides-Extra: tests
Requires-Dist: pytest ; extra == 'tests'
